ohgo/__init__.py
ohgo/exceptions.py
ohgo/image_handler.py
ohgo/ohgo_client.py
ohgo/rest_adapter.py
ohgo/models/__init__.py
ohgo/models/base_model.py
ohgo/models/camera.py
ohgo/models/construction.py
ohgo/models/dangerous_slowdown.py
ohgo/models/digital_sign.py
ohgo/models/incident.py
ohgo/models/models.py
ohgo/models/query_params.py
ohgo/models/travel_delay.py
ohgo/models/weather_sensor_site.py
ohgo/types/__init__.py
ohgo/types/enums.py
ohgo-1.0.3.dist-info/METADATA
ohgo-1.0.3.dist-info/WHEEL
ohgo-1.0.3.dist-info/licenses/LICENSE
ohgo-1.0.3.dist-info/RECORD
