Metadata-Version: 2.3
Name: ohgo
Version: 1.0.3
Summary: A wrapper for the OHGO API
Project-URL: Homepage, https://github.com/TomCasavant/ohgo-wrapper
Project-URL: Issues, https://github.com/TomCasavant/ohgo-wrapper/issues
Author-email: Tom Casavant <tfcasavant@gmail.com>
License-File: LICENSE
Keywords: api,cameras,ohgo,ohio,traffic,wrapper
Classifier: License :: OSI Approved :: MIT License
Classifier: Operating System :: OS Independent
Classifier: Programming Language :: Python :: 3
Classifier: Topic :: Internet
Classifier: Topic :: Software Development :: Libraries :: Python Modules
Classifier: Topic :: Utilities
Requires-Python: >=3.8
Requires-Dist: pillow
Requires-Dist: python-dateutil
Requires-Dist: requests
